liveinfo/__init__.py
liveinfo/cli.py
liveinfo/liveinfo.py
liveinfo/nicolive.py
liveinfo/ytlive.py
aoirint_liveinfo-0.1.11.dist-info/LICENSE
aoirint_liveinfo-0.1.11.dist-info/METADATA
aoirint_liveinfo-0.1.11.dist-info/WHEEL
aoirint_liveinfo-0.1.11.dist-info/entry_points.txt
aoirint_liveinfo-0.1.11.dist-info/top_level.txt
aoirint_liveinfo-0.1.11.dist-info/RECORD
