Metadata-Version: 2.1
Name: aoirint-liveinfo
Version: 0.1.11
Summary: UNKNOWN
Home-page: https://github.com/aoirint/liveinfopy
Author: aoirint
Author-email: aoirint@gmail.com
License: MIT
Platform: UNKNOWN
Classifier: Development Status :: 3 - Alpha
Classifier: License :: OSI Approved :: MIT License
Classifier: Programming Language :: Python
Classifier: Programming Language :: Python :: 3
Classifier: Programming Language :: Python :: 3.8
Classifier: Programming Language :: Python :: 3.9
Classifier: Programming Language :: Python :: 3.10
Classifier: Programming Language :: Python :: 3.11
Requires-Dist: requests
Requires-Dist: beautifulsoup4
Requires-Dist: html5lib
